asyncfile/__init__.py
asyncfile/classes.py
asyncfile/openup.py
asyncfile/threads.py
asyncfile/usefuls.py
asyncfile-1.0.0.dist-info/LICENSE
asyncfile-1.0.0.dist-info/METADATA
asyncfile-1.0.0.dist-info/WHEEL
asyncfile-1.0.0.dist-info/top_level.txt
asyncfile-1.0.0.dist-info/RECORD
