Metadata-Version: 2.1
Name: asyncfile
Version: 1.0.0
Summary: An asynchronous file handling module.
Home-page: https://github.com/try-fail1/asyncfile
Author: Ryan Vink
Author-email: ryantvink@gmail.com
License: MIT
Keywords: python,asyncio,fileio
Platform: UNKNOWN
Classifier: Framework :: AsyncIO
Classifier: Development Status :: 4 - Beta
Classifier: License :: OSI Approved :: MIT License
Classifier: Programming Language :: Python :: 3.5
Classifier: Programming Language :: Python :: 3.6
Classifier: Programming Language :: Python :: 3.7
Classifier: Programming Language :: Python :: 3.8
Classifier: Intended Audience :: Developers
Classifier: Natural Language :: English
Classifier: Topic :: Utilities
Requires-Python: >=3.6.0
